topsis_tanisha/__init__.py
topsis_tanisha/topsis.py
topsis_tanisha_102303545-0.0.2.dist-info/METADATA
topsis_tanisha_102303545-0.0.2.dist-info/WHEEL
topsis_tanisha_102303545-0.0.2.dist-info/entry_points.txt
topsis_tanisha_102303545-0.0.2.dist-info/top_level.txt
topsis_tanisha_102303545-0.0.2.dist-info/RECORD
