Metadata-Version: 2.4
Name: TOPSIS-TANISHA-102303545
Version: 0.0.2
Summary: A Python package implementing the TOPSIS decision making method
Author: Tanisha Dua
Author-email: tdua_be23@thapar.edu
Requires-Python: >=3.8
Requires-Dist: pandas
Requires-Dist: numpy
Requires-Dist: openpyxl
Dynamic: author
Dynamic: author-email
Dynamic: description-content-type
Dynamic: requires-dist
Dynamic: requires-python
Dynamic: summary
